MANIFEST.in
setup.py
TracKanbanBoard.egg-info/PKG-INFO
TracKanbanBoard.egg-info/SOURCES.txt
TracKanbanBoard.egg-info/dependency_links.txt
TracKanbanBoard.egg-info/entry_points.txt
TracKanbanBoard.egg-info/not-zip-safe
TracKanbanBoard.egg-info/requires.txt
TracKanbanBoard.egg-info/top_level.txt
trackanbanboard/__init__.py
trackanbanboard/kanbanboardmacro.py
trackanbanboard/htdocs/css/jquery-ui-1.9.2.custom.min.css
trackanbanboard/htdocs/css/kanbanboard.css
trackanbanboard/htdocs/css/images/ui-bg_flat_0_aaaaaa_40x100.png
trackanbanboard/htdocs/css/images/ui-bg_flat_100_fff7ae_40x100.png
trackanbanboard/htdocs/css/images/ui-bg_flat_75_ffffff_40x100.png
trackanbanboard/htdocs/css/images/ui-bg_glass_55_fbf9ee_1x400.png
trackanbanboard/htdocs/css/images/ui-bg_glass_65_ffffff_1x400.png
trackanbanboard/htdocs/css/images/ui-bg_glass_95_fef1ec_1x400.png
trackanbanboard/htdocs/css/images/ui-bg_highlight-soft_100_dadada_1x100.png
trackanbanboard/htdocs/css/images/ui-bg_highlight-soft_75_e6e6e6_1x100.png
trackanbanboard/htdocs/css/images/ui-icons_222222_256x240.png
trackanbanboard/htdocs/js/kanbanboard.js
trackanbanboard/htdocs/js/kanbanutil.js
trackanbanboard/htdocs/js/libs/jquery-1.8.3.js
trackanbanboard/htdocs/js/libs/jquery-ui-1.9.2.custom.min.js
trackanbanboard/htdocs/js/libs/knockout-2.2.0.js
trackanbanboard/htdocs/js/libs/knockout-sortable.min.js
trackanbanboard/htdocs/js/libs/knockout.mapping.js
trackanbanboard/templates/kanbanboard.html
trackanbanboard/templates/kanbanerror.html