Metadata-Version: 1.1
Name: TracKanbanBoard
Version: 0.1
Summary: Kanban board plugin for Trac
Home-page: http://projects.developer.nokia.com/TracKanbanBoard
Author: Arto Nykänen
Author-email: arto.nykanen@digia.com
License: BSD-new
Keywords: trac plugin kanban
Platform: UNKNOWN
Classifier: Development Status :: 4 - Beta
Classifier: Environment :: Plugins
Classifier: Environment :: Web Environment
Classifier: Framework :: Trac
Classifier: License :: OSI Approved :: BSD License
Classifier: Natural Language :: English
Classifier: Programming Language :: Python
